database_nosql_automation/__init__.py
database_nosql_automation/mongo_crud.py
database_automation_for_crud_operation-0.0.1.dist-info/LICENSE
database_automation_for_crud_operation-0.0.1.dist-info/METADATA
database_automation_for_crud_operation-0.0.1.dist-info/WHEEL
database_automation_for_crud_operation-0.0.1.dist-info/top_level.txt
database_automation_for_crud_operation-0.0.1.dist-info/RECORD
