Metadata-Version: 2.1
Name: database_automation_for_crud_operation
Version: 0.0.1
Summary: A python package for connecting with database.
Home-page: https://github.com/raftaarrashedin/database_automation_with_mongodb_python
Author: raftaarrashedin
Author-email: raftaarrashedin100@gmail.com
License: MIT
Project-URL: Bug Tracker, https://github.com/raftaarrashedin/database_automation_with_mongodb_python/issues
Classifier: Programming Language :: Python :: 3.7
Classifier: Programming Language :: Python :: 3.8
Classifier: Programming Language :: Python :: 3.9
Classifier: Operating System :: OS Independent
Requires-Python: >=3.7
License-File: LICENSE
Requires-Dist: ensure ==1.0.2
Requires-Dist: py-youtube ==1.1.7
Provides-Extra: testing
Requires-Dist: pytest >=7.1.3 ; extra == 'testing'
Requires-Dist: mypy >=0.971 ; extra == 'testing'
Requires-Dist: flake8 >=5.0.4 ; extra == 'testing'
Requires-Dist: tox >=3.25.1 ; extra == 'testing'
Requires-Dist: black >=22.8.0 ; extra == 'testing'
